BaseAPI.py
setup.cfg
setup.py
BaseAPI.egg-info/PKG-INFO
BaseAPI.egg-info/SOURCES.txt
BaseAPI.egg-info/dependency_links.txt
BaseAPI.egg-info/requires.txt
BaseAPI.egg-info/top_level.txt
test/test_api.py