Metadata-Version: 1.1
Name: BaseAPI
Version: 0.1.1
Summary: A base class for implementing an HTTP API wrapper
Home-page: https://github.com/jameswenzel/BaseAPI
Author: James Wenzel
Author-email: wenzel.james.r@gmail.com
License: Apache License 2.0
Download-URL: http://github.com/jameswenzel/BaseAPI/tarball0.1.1
Keywords: http,API,REST,RESTful,API
Platform: UNKNOWN
